{"code_geographique":"41060","nom":"East Angus","annee":2024,"genere":"2026-06-07T20:15:53.974180+00:00","dashboard":{"code_geographique":"41060","nom":"East Angus","region_administrative":"Estrie (05)","population":4267,"classe_population":"2 000 à 4 999","communaute_metropolitaine":null,"mrc":"MRC Le Haut-Saint-François (410)","superficie_km2":8.32,"latitude":null,"longitude":null,"site_web_officiel":"https://www.eastangus.ca","taux_global_taxation":1.0365,"indice_effort_fiscal":84.8,"charge_fiscale_logement":1892.0,"eval_moy_residence":194186.0,"richesse_fonciere":377010100.0,"rfu_par_habitant":null,"charges_totales":8966228.0,"charge_nette_rfu":null,"charges_par_habitant":null,"revenus_totaux":null,"dette_nette_lt":null,"endettement_rfu":null,"dette_par_habitant":null,"dette_nette_habitant":1917.55,"pct_service_dette":null,"excedent_fonctionnement":null,"excedent_accumule":2046010.0,"surplus_annuel":null,"remuneration_totale":null,"pct_remuneration":null,"pct_base_residentielle":11.05,"pct_base_autre":0.19,"pct_base_compensations":3.96,"nb_logements":298760.0,"annee_fiscale":2024},"elus":[{"nom":"Guillaume Landry","poste":"Maire"},{"nom":"Sabrina Denault Lapointe","poste":"Conseiller(ère)"},{"nom":"Mathieu Skelling","poste":"Conseiller(ère)"},{"nom":"Demmi Dolbec","poste":"Conseiller(ère)"},{"nom":"Antoni Dumont","poste":"Conseiller(ère)"},{"nom":"Normand Graillon","poste":"Conseiller(ère)"},{"nom":"Nicole Bernier","poste":"Conseiller(ère)"}],"categories_depenses":[]}