{"code_geographique":"42098","nom":"Richmond","annee":2025,"genere":"2026-06-08T21:56:08.901927+00:00","dashboard":{"code_geographique":"42098","nom":"Richmond","region_administrative":"Estrie (05)","population":3453,"classe_population":"2 000 à 4 999","communaute_metropolitaine":null,"mrc":"MRC Le Val-Saint-François (420)","superficie_km2":6.96,"latitude":null,"longitude":null,"site_web_officiel":"https://www.richmond.quebec","taux_global_taxation":1.1575,"indice_effort_fiscal":77.87,"charge_fiscale_logement":1806.0,"eval_moy_residence":158610.0,"richesse_fonciere":274068000.0,"rfu_par_habitant":null,"charges_totales":6977523.0,"charge_nette_rfu":null,"charges_par_habitant":null,"revenus_totaux":null,"dette_nette_lt":null,"endettement_rfu":null,"dette_par_habitant":null,"dette_nette_habitant":1449.26,"pct_service_dette":null,"excedent_fonctionnement":null,"excedent_accumule":1285235.0,"surplus_annuel":null,"remuneration_totale":null,"pct_remuneration":null,"pct_base_residentielle":20.5,"pct_base_autre":0.32,"pct_base_compensations":1.32,"nb_logements":302508.0,"annee_fiscale":2025},"elus":[],"categories_depenses":[]}