{"code_geographique":"45100","nom":"Saint-Étienne-de-Bolton","annee":2024,"genere":"2026-06-07T20:15:53.974180+00:00","dashboard":{"code_geographique":"45100","nom":"Saint-Étienne-de-Bolton","region_administrative":"Estrie (05)","population":902,"classe_population":"500 à 999","communaute_metropolitaine":null,"mrc":"MRC Memphrémagog (450)","superficie_km2":48.76,"latitude":null,"longitude":null,"site_web_officiel":"https://www.sedb.qc.ca","taux_global_taxation":0.4106,"indice_effort_fiscal":86.92,"charge_fiscale_logement":2116.0,"eval_moy_residence":568758.0,"richesse_fonciere":355783303.0,"rfu_par_habitant":null,"charges_totales":2061777.0,"charge_nette_rfu":null,"charges_par_habitant":null,"revenus_totaux":null,"dette_nette_lt":null,"endettement_rfu":null,"dette_par_habitant":null,"dette_nette_habitant":418.47,"pct_service_dette":null,"excedent_fonctionnement":null,"excedent_accumule":820826.0,"surplus_annuel":null,"remuneration_totale":null,"pct_remuneration":null,"pct_base_residentielle":2.75,"pct_base_autre":2.26,"pct_base_compensations":8.07,"nb_logements":440605.0,"annee_fiscale":2024},"elus":[{"nom":"Diane Desjardins","poste":"Maire"},{"nom":"Harry Bird","poste":"Conseiller(ère)"},{"nom":"Jocelyn Brasseur","poste":"Conseiller(ère)"},{"nom":"Vincent Jarry","poste":"Conseiller(ère)"},{"nom":"Christine Boutin","poste":"Conseiller(ère)"},{"nom":"Robert Bergeron","poste":"Conseiller(ère)"},{"nom":"Alexandre Berger","poste":"Conseiller(ère)"}],"categories_depenses":[]}