{"code_geographique":"49113","nom":"Saint-Guillaume","annee":2025,"genere":"2026-06-08T14:18:34.956390+00:00","dashboard":{"code_geographique":"49113","nom":"Saint-Guillaume","region_administrative":"Centre-du-Québec (17)","population":1495,"classe_population":"1 000 à 1 999","communaute_metropolitaine":null,"mrc":"MRC Drummond (490)","superficie_km2":88.38,"latitude":null,"longitude":null,"site_web_officiel":"https://www.saintguillaume.ca","taux_global_taxation":0.5327,"indice_effort_fiscal":29.78,"charge_fiscale_logement":1146.0,"eval_moy_residence":233431.0,"richesse_fonciere":144340000.0,"rfu_par_habitant":null,"charges_totales":3675162.0,"charge_nette_rfu":null,"charges_par_habitant":null,"revenus_totaux":null,"dette_nette_lt":null,"endettement_rfu":null,"dette_par_habitant":null,"dette_nette_habitant":2478.34,"pct_service_dette":null,"excedent_fonctionnement":null,"excedent_accumule":485627.0,"surplus_annuel":null,"remuneration_totale":null,"pct_remuneration":null,"pct_base_residentielle":4.29,"pct_base_autre":64.99,"pct_base_compensations":0.95,"nb_logements":548110.0,"annee_fiscale":2025},"elus":[{"nom":"Alain Laprade","poste":"Maire"},{"nom":"Dominique Laforce","poste":"Conseiller(ère)"},{"nom":"Christian Lemay","poste":"Conseiller(ère)"},{"nom":"Marylène Charest","poste":"Conseiller(ère)"},{"nom":"Mathieu Labrecque","poste":"Conseiller(ère)"},{"nom":"Dominic Doyon","poste":"Conseiller(ère)"},{"nom":"Guylaine Lacharité","poste":"Conseiller(ère)"}],"categories_depenses":[]}