{"code_geographique":"56060","nom":"Sainte-Anne-de-Sabrevois","annee":2025,"genere":"2026-06-01T19:38:34.982701+00:00","dashboard":{"code_geographique":"56060","nom":"Sainte-Anne-de-Sabrevois","region_administrative":"Montérégie (16)","population":2307,"classe_population":"2 000 à 4 999","communaute_metropolitaine":null,"mrc":"MRC Le Haut-Richelieu (560)","superficie_km2":48.43,"latitude":null,"longitude":null,"site_web_officiel":"https://sainte-anne-de-sabrevois.com","taux_global_taxation":null,"indice_effort_fiscal":60.5,"charge_fiscale_logement":null,"eval_moy_residence":379341.0,"richesse_fonciere":363284500.0,"rfu_par_habitant":null,"charges_totales":null,"charge_nette_rfu":null,"charges_par_habitant":null,"revenus_totaux":null,"dette_nette_lt":null,"endettement_rfu":null,"dette_par_habitant":null,"pct_service_dette":null,"excedent_fonctionnement":null,"surplus_annuel":null,"remuneration_totale":null,"pct_remuneration":null,"pct_base_residentielle":5.8,"pct_base_autre":33.04,"pct_base_compensations":0.65,"nb_logements":518106.0,"annee_fiscale":2025},"elus":[],"categories_depenses":[]}